r_ascan-0.1.1.dist-info/licenses/LICENSE
rascan/__init__.py
rascan/app.py
rascan/config.py
rascan/module/__init__.py
rascan/module/ml_optimizer.py
rascan/module/other.py
rascan/resources/common_endpoints.txt
rascan/resources/directories.txt
rascan/resources/http_smuggling_payloads.json
rascan/resources/sensitive_files.txt
rascan/scanners/access_control.py
rascan/scanners/broken_access_control.py
rascan/scanners/command_injection.py
rascan/scanners/content_leak.py
rascan/scanners/deployment_config.py
rascan/scanners/endpoint_finder.py
rascan/scanners/entry_points.py
rascan/scanners/enumerate_services.py
rascan/scanners/enumeration_directory.py
rascan/scanners/fingerprint_web_server.py
rascan/scanners/frameworks_components.py
rascan/scanners/hosting_environment.py
rascan/scanners/http_smuggler.py
rascan/scanners/ldap_injection.py
rascan/scanners/lfi.py
rascan/scanners/metafiles_leak.py
rascan/scanners/open_redirect.py
rascan/scanners/rate_limiting.py
rascan/scanners/rce.py
rascan/scanners/security_headers.py
rascan/scanners/sensitive_files.py
rascan/scanners/sqli.py
rascan/scanners/ssrf.py
rascan/scanners/ssti.py
rascan/scanners/technologies.py
rascan/scanners/top_25_owasp_full_scanner.py
rascan/scanners/web_extractor.py
rascan/scanners/xss.py
rascan/scanners/exploits/apache2_struts.py
rascan/scanners/exploits/elaina_cve_2025_32433.py
rascan/scanners/exploits/php_unit_rce.py
r_ascan-0.1.1.dist-info/METADATA
r_ascan-0.1.1.dist-info/WHEEL
r_ascan-0.1.1.dist-info/entry_points.txt
r_ascan-0.1.1.dist-info/top_level.txt
r_ascan-0.1.1.dist-info/RECORD
