Metadata-Version: 2.4
Name: R-AScan
Version: 0.1.1
Summary: Rusher Automatic Scan
Author-email: Afrizal FA <afrzlf4@gmail.com>
Requires-Python: >=3.10
License-File: LICENSE
Dynamic: license-file
